labpythonlib/__init__.py
labpythonlib/lab_functions.py
labpythonlib/lab_markers.py
labpythonlib-4.0.0.dist-info/LICENSE.txt
labpythonlib-4.0.0.dist-info/METADATA
labpythonlib-4.0.0.dist-info/WHEEL
labpythonlib-4.0.0.dist-info/top_level.txt
labpythonlib-4.0.0.dist-info/RECORD
